opf/__init__.py
opf/core/__init__.py
opf/core/acopf.py
opf/core/acopf_exp.py
opf/core/base.py
opf/core/dcopf.py
opf/core/dcopf_exp.py
opf/core/dcopf_ptdf.py
opf/core/func.py
opf/core/lodf.py
opf/core/ptdf.py
opf/core/scdcopf.py
opf/core/scdcopf_ccga.py
opf/core/scdcopf_exp.py
opf/core/utils.py
opf/core/warmstart.py
opf/io/__init__.py
opf/io/common.py
opf/io/io.py
opf/io/matpower.py
opf-0.3.1.dist-info/LICENSE.md
opf-0.3.1.dist-info/METADATA
opf-0.3.1.dist-info/WHEEL
opf-0.3.1.dist-info/top_level.txt
opf-0.3.1.dist-info/RECORD
