Metadata-Version: 2.1
Name: opf
Version: 0.3.1
Summary: PyOPF: Optimal Power Flow Modeling in Python
Author: Seonho Park
Author-email: park.seonho@gmail.com
License: MIT
Project-URL: Github, https://github.com/seonho-park/PyOPF
Classifier: Intended Audience :: Developers
Classifier: Intended Audience :: Science/Research
Classifier: Topic :: Scientific/Engineering
Classifier: Topic :: Scientific/Engineering :: Mathematics
Classifier: Topic :: Scientific/Engineering :: Artificial Intelligence
Classifier: Topic :: Software Development
Classifier: Topic :: Software Development :: Libraries
Classifier: Topic :: Software Development :: Libraries :: Python Modules
Classifier: License :: OSI Approved :: MIT License
Classifier: Programming Language :: Python
Classifier: Programming Language :: Python :: 3
Classifier: Programming Language :: Python :: 3.8
Classifier: Programming Language :: Python :: 3.9
Classifier: Programming Language :: Python :: 3.10
Classifier: Operating System :: OS Independent
Requires-Python: >=3.8
License-File: LICENSE.md
Requires-Dist: typing-extensions
Requires-Dist: pyomo >=6.5.0
Requires-Dist: numpy >=1.22.3
Requires-Dist: scipy >=1.10.1
